tree_cli/__init__.py
tree_cli/cli.py
gabbium_tree-1.0.0.dist-info/METADATA
gabbium_tree-1.0.0.dist-info/WHEEL
gabbium_tree-1.0.0.dist-info/entry_points.txt
gabbium_tree-1.0.0.dist-info/licenses/LICENSE
gabbium_tree-1.0.0.dist-info/RECORD
