Metadata-Version: 2.4
Name: gabbium-tree
Version: 1.0.0
Summary: CLI to print a project directory tree
Author: Gabriel Abreu (@gabbium)
License: MIT
License-File: LICENSE
Requires-Python: >=3.8
